LICENSE
MANIFEST.in
README.rst
setup.py
dj_mongo_reader2.egg-info/PKG-INFO
dj_mongo_reader2.egg-info/SOURCES.txt
dj_mongo_reader2.egg-info/dependency_links.txt
dj_mongo_reader2.egg-info/requires.txt
dj_mongo_reader2.egg-info/top_level.txt
djmongoreader/__init__.py
djmongoreader/models.py
djmongoreader/mongoreader.py
djmongoreader/tests.py
djmongoreader/urls.py
djmongoreader/utility.py
djmongoreader/views.py
djmongoreader/static/dj-mongo-reader/js/mongoreader.js
djmongoreader/static/dj-mongo-reader/js/rendertable.js
djmongoreader/templates/dj-mongo-reader/core.html
djmongoreader/templates/dj-mongo-reader/table.html
example/sampleapp/Procfile
example/sampleapp/data_100.json
example/sampleapp/gen_testdata.py
example/sampleapp/manage.py
example/sampleapp/requirements.txt
example/sampleapp/sampleapp/__init__.py
example/sampleapp/sampleapp/security.py
example/sampleapp/sampleapp/settings.py
example/sampleapp/sampleapp/urls.py
example/sampleapp/sampleapp/views.py
example/sampleapp/sampleapp/wsgi.py
example/sampleapp/templates/base.html
example/sampleapp/templates/query.html
example/sampleapp/templates/readme.html
example/sampleapp/templates/dj-mongo-reader/table.html