Metadata-Version: 1.1
Name: dj-mongo-reader2
Version: 1.1.0
Summary: A Django app can be used to query and render MongoDB data
Home-page: https://github.com/tofu0913/dj-mongo-reader/
Author: Fan Fei, Neil Chen, Cliff Chen
Author-email: tofu0913@gmail.com
License: GPL v2.0
Platform: UNKNOWN
Classifier: Environment :: Web Environment
Classifier: Framework :: Django
Classifier: Intended Audience :: Developers
Classifier: License :: OSI Approved :: GNU General Public License v2 (GPLv2)
Classifier: Operating System :: OS Independent
Classifier: Programming Language :: Python
Classifier: Programming Language :: Python :: 2
Classifier: Programming Language :: Python :: 2.6
Classifier: Programming Language :: Python :: 2.7
Classifier: Topic :: Internet :: WWW/HTTP
Classifier: Topic :: Internet :: WWW/HTTP :: Dynamic Content
Classifier: Topic :: Database
Classifier: Topic :: Database :: Database Engines/Servers
Classifier: Topic :: Database :: Front-Ends
